LICENSE.txt
MANIFEST.in
README.rst
setup.cfg
setup.py
scripts/xflow-exec
scripts/xflow-execall
scripts/xflow-run
scripts/xflow-stat
test/__init__.py
test/test_error_handling.py
test/test_temp_filehandling.py
xbowflow/__init__.py
xbowflow/_version.py
xbowflow/clients.py
xbowflow/filehandling.py
xbowflow/pipelines.py
xbowflow/xflowlib.py
xbowflow.egg-info/PKG-INFO
xbowflow.egg-info/SOURCES.txt
xbowflow.egg-info/dependency_links.txt
xbowflow.egg-info/not-zip-safe
xbowflow.egg-info/requires.txt
xbowflow.egg-info/top_level.txt